LICENSE.txt
README.md
setup.cfg
setup.py
trappist/__init__.py
trappist/hash.py
trappist/jsonconverter.py
trappist/smtpmail.py
trappistframework.egg-info/PKG-INFO
trappistframework.egg-info/SOURCES.txt
trappistframework.egg-info/dependency_links.txt
trappistframework.egg-info/top_level.txt