Metadata-Version: 2.1
Name: trappistframework
Version: 0.0.1
Summary: Aykut Cantürk Python Library
Author: Aykut Cantürk
Author-email: canturk.aykut@gmail.com
License-File: LICENSE.txt
